nirjas/__init__.py
nirjas/binder.py
nirjas/main.py
nirjas/languages/__init__.py
nirjas/languages/c.py
nirjas/languages/c_sharp.py
nirjas/languages/cpp.py
nirjas/languages/css.py
nirjas/languages/dart.py
nirjas/languages/go.py
nirjas/languages/haskell.py
nirjas/languages/html.py
nirjas/languages/java.py
nirjas/languages/javascript.py
nirjas/languages/julia.py
nirjas/languages/kotlin.py
nirjas/languages/matlab.py
nirjas/languages/perl.py
nirjas/languages/php.py
nirjas/languages/python.py
nirjas/languages/r.py
nirjas/languages/ruby.py
nirjas/languages/rust.py
nirjas/languages/scala.py
nirjas/languages/scss.py
nirjas/languages/shell.py
nirjas/languages/sql.py
nirjas/languages/swift.py
nirjas/languages/text.py
nirjas/languages/typescript.py
nirjas/languages/tests/__init__.py
nirjas/languages/tests/test_c.py
nirjas/languages/tests/test_c_sharp.py
nirjas/languages/tests/test_cpp.py
nirjas/languages/tests/test_css.py
nirjas/languages/tests/test_dart.py
nirjas/languages/tests/test_go.py
nirjas/languages/tests/test_haskell.py
nirjas/languages/tests/test_html.py
nirjas/languages/tests/test_java.py
nirjas/languages/tests/test_javascript.py
nirjas/languages/tests/test_julia.py
nirjas/languages/tests/test_kotlin.py
nirjas/languages/tests/test_matlab.py
nirjas/languages/tests/test_perl.py
nirjas/languages/tests/test_php.py
nirjas/languages/tests/test_python.py
nirjas/languages/tests/test_r.py
nirjas/languages/tests/test_ruby.py
nirjas/languages/tests/test_rust.py
nirjas/languages/tests/test_scala.py
nirjas/languages/tests/test_scss.py
nirjas/languages/tests/test_shell.py
nirjas/languages/tests/test_sql.py
nirjas/languages/tests/test_swift.py
nirjas/languages/tests/test_typescript.py
nirjas/output/__init__.py
nirjas/output/multi_line.py
nirjas/output/output.py
nirjas/output/scan_output.py
nirjas/output/single_line.py
Nirjas-1.0.1.dist-info/LICENSE
Nirjas-1.0.1.dist-info/METADATA
Nirjas-1.0.1.dist-info/WHEEL
Nirjas-1.0.1.dist-info/entry_points.txt
Nirjas-1.0.1.dist-info/top_level.txt
Nirjas-1.0.1.dist-info/RECORD
