Metadata-Version: 2.1
Name: Nirjas
Version: 1.0.1
Summary: A Python library to extract comments and source code out of your file(s)
Home-page: https://github.com/fossology/nirjas
Author: Ayush Bhardwaj, Kaushlendra Pratap
Author-email: classicayush@gmail.com, kaushlendrapratap.9837@gmail.com
License: LGPL-2.1-or-later
Keywords: Nirjas,Code Comment,Comment Extractor,Code Comment Extractor,Source Code Extractor,Source Extractor
Platform: any
Classifier: Development Status :: 5 - Production/Stable
Classifier: License :: OSI Approved :: GNU Lesser General Public License v2 or later (LGPLv2+)
Classifier: Programming Language :: Python :: 3 :: Only
Classifier: Intended Audience :: Developers
Classifier: Intended Audience :: Legal Industry
Classifier: Topic :: Utilities
Classifier: Topic :: Software Development
Classifier: Topic :: Text Processing
Requires-Python: >=3
